cyberiadaml_py/__init__.py
cyberiadaml_py/cyberiadaml_builder.py
cyberiadaml_py/cyberiadaml_parser.py
cyberiadaml_py/types/cgml_scheme.py
cyberiadaml_py/types/common.py
cyberiadaml_py/types/elements.py
cyberiadaml_py/utils.py
cyberiadaml_py-1.2.3.dist-info/LICENSE
cyberiadaml_py-1.2.3.dist-info/METADATA
cyberiadaml_py-1.2.3.dist-info/WHEEL
cyberiadaml_py-1.2.3.dist-info/RECORD
