Metadata-Version: 2.1
Name: cyberiadaml-py
Version: 1.2.3
Summary: The Python 3 library for processing the CyberiadaML state machine graphs
Author: L140-beep
Author-email: kartoshka0302@mail.ru
Requires-Python: >=3.10,<4
Classifier: Programming Language :: Python :: 3
Classifier: Programming Language :: Python :: 3.10
Classifier: Programming Language :: Python :: 3.11
Classifier: Programming Language :: Python :: 3.12
Requires-Dist: pydantic (>=2.6.1,<3.0.0)
Requires-Dist: xmltodict (>=0.13.0,<0.14.0)
